<annotation>
	<folder>resize</folder>
	<filename>IMG_20191128_120334_3.jpg</filename>
	<path>C:\Users\ProvaTF\Desktop\resize\IMG_20191128_120334_3.jpg</path>
	<source>
		<database>Unknown</database>
	</source>
	<size>
		<width>800</width>
		<height>600</height>
		<depth>3</depth>
	</size>
	<segmented>0</segmented>
	<object>
		<name>bianca</name>
		<pose>Unspecified</pose>
		<truncated>0</truncated>
		<difficult>0</difficult>
		<bndbox>
			<xmin>365</xmin>
			<ymin>75</ymin>
			<xmax>532</xmax>
			<ymax>245</ymax>
		</bndbox>
	</object>
	<object>
		<name>nera</name>
		<pose>Unspecified</pose>
		<truncated>0</truncated>
		<difficult>0</difficult>
		<bndbox>
			<xmin>472</xmin>
			<ymin>182</ymin>
			<xmax>662</xmax>
			<ymax>371</ymax>
		</bndbox>
	</object>
</annotation>
